lime_nda/__init__.py
lime_nda/nda_functions.py
lime_nda/nda_version_8_0.py
lime_nda-0.1.0.dist-info/LICENSE
lime_nda-0.1.0.dist-info/METADATA
lime_nda-0.1.0.dist-info/WHEEL
lime_nda-0.1.0.dist-info/top_level.txt
lime_nda-0.1.0.dist-info/RECORD
