Metadata-Version: 2.1
Name: lime-nda
Version: 0.1.0
Summary: Python Package for working with NDA files, specifically for people at Lime.AI
Author-email: Lime CellTesting <vividhgarg@outlook.com>
Project-URL: Homepage, https://github.com/vividh-garg/NDA
Project-URL: Bug Tracker, https://github.com/vividh-garg/NDA/issues
Classifier: Programming Language :: Python :: 3
Classifier: License :: OSI Approved :: MIT License
Classifier: Operating System :: OS Independent
Requires-Python: >=3.8
License-File: LICENSE
